cloud_blobstore/__init__.py
cloud_blobstore/gs.py
cloud_blobstore/s3.py
cloud_blobstore-3.1.0.dist-info/METADATA
cloud_blobstore-3.1.0.dist-info/RECORD
cloud_blobstore-3.1.0.dist-info/WHEEL
cloud_blobstore-3.1.0.dist-info/top_level.txt
