Metadata-Version: 2.1
Name: cloud-blobstore
Version: 3.1.0
Summary: Abstraction layer for cloud blobstores.
Home-page: https://github.com/chanzuckerberg/cloud-blobstore
Author: Human Cell Atlas contributors
Author-email: tonytung@chanzuckerberg.com
License: Apache Software License
Platform: MacOS X
Platform: Posix
Classifier: Intended Audience :: Developers
Classifier: License :: OSI Approved :: Apache Software License
Classifier: Operating System :: MacOS :: MacOS X
Classifier: Operating System :: POSIX
Classifier: Programming Language :: Python
Classifier: Programming Language :: Python :: 3.6
Classifier: Topic :: Software Development :: Libraries :: Python Modules
Requires-Dist: boto3
Requires-Dist: google-cloud-storage (>=1.7.0)
Requires-Dist: requests
